rwkv/__init__.py
rwkv/model.py
rwkv/rwkv_tokenizer.py
rwkv/rwkv_vocab_v20230424.txt
rwkv/utils.py
rwkv/cuda/att_one.cu
rwkv/cuda/att_one_v5.cu
rwkv/cuda/att_seq.cu
rwkv/cuda/element_wise.h
rwkv/cuda/ffn.cu
rwkv/cuda/gemm_fp16_cublas.cpp
rwkv/cuda/operators.cu
rwkv/cuda/util.h
rwkv/cuda/wrapper.cpp
rwkv_beta-0.8.5.dist-info/LICENSE
rwkv_beta-0.8.5.dist-info/METADATA
rwkv_beta-0.8.5.dist-info/WHEEL
rwkv_beta-0.8.5.dist-info/top_level.txt
rwkv_beta-0.8.5.dist-info/RECORD
