Metadata-Version: 2.1
Name: rwkv-beta
Version: 0.8.5
Summary: The RWKV Language Model
Author: Bo PENG
Project-URL: Homepage, https://github.com/BlinkDL/ChatRWKV
Project-URL: Bug Tracker, https://github.com/BlinkDL/ChatRWKV/issues
Classifier: Programming Language :: Python :: 3
Classifier: License :: OSI Approved :: Apache Software License
Classifier: Operating System :: OS Independent
Requires-Python: >=3.7
License-File: LICENSE
Requires-Dist: tokenizers >=0.13.2
